<?xml version="1.0" encoding="utf-8"?>
<savedqueries xmlns:xsi="http://www.w3.org/2001/XMLSchema-instance">
  <savedquery>
    <IsCustomizable>1</IsCustomizable>
    <CanBeDeleted>0</CanBeDeleted>
    <isquickfindquery>0</isquickfindquery>
    <isprivate>0</isprivate>
    <isdefault>1</isdefault>
    <savedqueryid>{5f9857bf-a656-4db2-9aef-16c1ee049b0c}</savedqueryid>
    <layoutxml>
      <grid name="cat_themes" jump="cat_name" select="1" icon="1" preview="1">
        <row name="cat_theme" id="cat_themeid">
          <cell name="cat_name" width="300" />
          <cell name="createdon" width="125" />
        </row>
      </grid>
    </layoutxml>
    <querytype>2</querytype>
    <fetchxml>
      <fetch version="1.0" mapping="logical">
        <entity name="cat_theme">
          <attribute name="cat_themeid" />
          <attribute name="cat_name" />
          <attribute name="createdon" />
          <order attribute="cat_name" descending="false" />
          <filter type="and">
            <condition attribute="statecode" operator="eq" value="0" />
          </filter>
        </entity>
      </fetch>
    </fetchxml>
    <IntroducedVersion>1.0.0.0</IntroducedVersion>
    <LocalizedNames>
      <LocalizedName description="Theme Associated View" languagecode="1033" />
    </LocalizedNames>
  </savedquery>
</savedqueries>